tlacli/__init__.py
tlacli/cfg.py
tlacli/tla2tools.jar
tlacli/tlacli.py
tlacli/tools/__init__.py
tlacli/tools/pluscal.py
tlacli/tools/tlc.py
tlacli-0.0.1.dist-info/LICENSE.txt
tlacli-0.0.1.dist-info/METADATA
tlacli-0.0.1.dist-info/WHEEL
tlacli-0.0.1.dist-info/entry_points.txt
tlacli-0.0.1.dist-info/top_level.txt
tlacli-0.0.1.dist-info/RECORD
