Metadata-Version: 2.1
Name: tlacli
Version: 0.0.1
Summary: A wrapper script for running TLA+ from the command line
Home-page: https://github.com/hwayne/tlacli
Author: Hillel Wayne
Author-email: h@hillelwayne.com
License: UNKNOWN
Platform: UNKNOWN
Classifier: Development Status :: 3 - Alpha
Classifier: Intended Audience :: Developers
Classifier: Programming Language :: Python :: 3
Classifier: Topic :: Software Development
Classifier: Topic :: Software Development :: Libraries :: Java Libraries
Classifier: License :: OSI Approved :: MIT License
Classifier: Operating System :: OS Independent
Requires-Python: >=3.7
